Workbook

Sheet Supuestos
A1: Variable | B1: Valor_Base | C1: Valor_Pesimista | D1: Valor_Optimista
A2: Precio_robot | B2: 750000 | C2: 800000 | D2: 700000
A3: Ahorro_por_cirugia | B3: 1929 | C3: 1500 | D3: 2200
A4: Volumen_anual_grande | B4: 300 | C4: 250 | D4: 350
A5: Volumen_anual_chico | B5: 40 | C5: 50 | D5: 60
A6: Volumen_anual_publico | B6: 100 | C6: 125 | D6: 150
A7: Mantenimiento_anual | B7: 35000 | C7: 40000 | D7: 30000
A8: % Cuota de Mercado (SOM) | B8: 0.1 | C8: 0.05 | D8: 0.15

Sheet Competencia_Precio
A1: Marca Robot | B1: Modelo | C1: Precio_Compra_Min_USD | D1: Precio_Compra_Max_USD | E1: Precio Compra Promedio USD | F1: Costo_Mantenimiento_Min_USD | G1: Costo_Mantenimiento_Max_USD | H1: Costo_ Mantenimiento_ Promedio USD | I1: Costo_Consumibles_Min_USD | J1: Costo_Consumibles_Max_USD | K1: Costo_ Consumibles_ Promedio_ USD | L1: Vida_Util_Min_Anios | M1: Vida_Util_Max_Anios | N1: Vida_ Util_ Promedio_ Anios | O1: Diferencial_ Tecnico | P1: Venta CAPEX tradicional (1=Si_0=No) | Q1: Ofrece_ Leasing_ (1=Si _0=No) | R1: Ofrece_ Pago_ por_ Uso_ (1=Si_ 0=No) | S1: Ofrece_ Modelo_ Mixto_ (1=Si_0=No)
A2: da Vinci | B2: Xi / X | C2: 1800000 | D2: 2300000 | E2: 2050000 | F2: 150000 | G2: 180000 | H2: 165000 | I2: 2000 | J2: 3500 | K2: 2750 | L2: 7 | M2: 10 | N2: 8.5 | O2: Gold Standard - Sin Háptica | P2: 1 | Q2: 1 | R2: 0 | S2: 1 | U2: 1 | V2: SI
A3: Versius | B3: CMR Surgical | C3: 1200000 | D3: 1500000 | E3: 1350000 | F3: 80000 | G3: 120000 | H3: 100000 | I3: 800 | J3: 1500 | K3: 1150 | L3: 8 | M3: 10 | N3: 9 | O3: Modular - Sin Háptica | P3: 1 | Q3: 1 | R3: 0 | S3: 1 | U3: 0 | V3: NO
A4: Hugo RAS | B4: Medtronic | C4: 1000000 | D4: 1300000 | E4: 1150000 | F4: 70000 | G4: 100000 | H4: 85000 | I4: 700 | J4: 1200 | K4: 950 | L4: 8 | M4: 10 | N4: 9 | O4: Consola Abierta | P4: 1 | Q4: 1 | R4: 0 | S4: 1
A5: Justina | B5: Prototipo | C5: 750000 | D5: 750000 | E5: =Supuestos!B2 -> 750000 | F5: 25000 | G5: 40000 | H5: =Supuestos!B7 -> 35000 | I5: 300 | J5: 600 | K5: 450 | L5: 10 | M5: 12 | N5: 11 | O5: CON HÁPTICA (Tacto Real) | P5: 1 | Q5: 1 | R5: 1 | S5: 1
F8: Venta CAPEX tradicional
F9: SI
F10: SI
F11: SI
F12: SI

Sheet TAM-SAM-SOM
A1: País | B1: Población 2024 | C1: Incidencia Cáncer Renal (x100k) | D1: Casos Nuevos Estimados 2022 | E1: % Casos Operables | F1: Nefrectomías Oncológicas | G1: Nefrectomías Donante Vivo | H1: Total Cirugías (TAM) | I1: % Penetración Robótica Estimada | J1: Mercado Direccionable (SAM) | K1: Gasto Salud p/c (USD) año 2023 | L1: Cuota de Mercado Objetivo (SOM) | O1: Poblacion | P1: https://data.worldbank.org/indicator/SP.POP.TOTL
A2: EE.UU. | B2: 340110988 | C2: 12.2 | D2: 71759 | E2: 0.7 | F2: =SUM(D2*E2) -> 50231.3 | G2: 6419 | H2: =SUM(F2+G2) -> 56650.3 | I2: 0.3 | J2: =SUM(H2*I2) -> 16995.09 | K2: 13473.193 | L2: =SUM(J2*Supuestos!$B$8) -> 1699.509 | O2: Gasto Salud p/c (USD) | P2: https://data.worldbank.org/indicator/SH.XPD.CHEX.PC.CD?name_desc=true
A3: China | B3: 1408975000 | C3: 4.1 | D3: 73656 | E3: 0.6 | F3: =SUM(D3*E3) -> 44193.6 | G3: 3555 | H3: =SUM(F3+G3) -> 47748.6 | I3: 0.1 | J3: =SUM(H3*I3) -> 4774.86 | K3: 763.37762 | L3: =SUM(J3*Supuestos!$B$8) -> 477.486 | O3: Casos Nuevos Estimados | P3: https://gco.iarc.who.int/today/en/fact-sheets-populations#countries
A4: Reino Unido | B4: 69226000 | C4: 10.5 | D4: 13714 | E4: 0.65 | F4: =SUM(D4*E4) -> 8914.1 | G4: 948 | H4: =SUM(F4+G4) -> 9862.1 | I4: 0.15 | J4: =SUM(H4*I4) -> 1479.315 | K4: 5407.1704 | L4: =SUM(J4*Supuestos!$B$8) -> 147.9315 | O4: donantes vivos | P4: newsletter 2025
A5: España | B5: 48848840 | C5: 10.1 | D5: 8686 | E5: 0.7 | F5: =SUM(D5*E5) -> 6080.2 | G5: 398 | H5: =SUM(F5+G5) -> 6478.2 | I5: 0.15 | J5: =SUM(H5*I5) -> 971.73 | K5: 3106.6201 | L5: =SUM(J5*Supuestos!$B$8) -> 97.173 | O5: % Casos Operables | P5: https://www.europeanurology.com/article/S0302-2838(25)00139-3/fulltext
A6: Argentina | B6: 45696159 | C6: 7.5 | D6: 4908 | E6: 0.6 | F6: =SUM(D6*E6) -> 2944.8 | G6: 241 | H6: =SUM(F6+G6) -> 3185.8 | I6: 0.05 | J6: =SUM(H6*I6) -> 159.29 | K6: 1456.986 | L6: =SUM(J6*Supuestos!$B$8) -> 15.929 | O6: Incidencia Cáncer Renal (x100k) Columna ASR WORLD | P6: https://gco.iarc.fr/today/en/dataviz/tables?mode=population&cancers=29&group_populations=0&multiple_populations=1&populations=100_104_108_112_116_12_120_124_132_140_144_148_152_160_170_174_178_180_188_191_192_196_203_204_208_214_218_222_226_231_232_233_24_242_246_250_254_258_262_266_268_270_275_276_288_300_31_312_316_32_320_324_328_332_340_348_352_356_36_360_364_368_372_376_380_384_388_392_398_4_40_400_404_408_410_414_417_418_422_426_428_430_434_44_440_442_450_454_458_462_466_470_474_478_48_480_484_496_498_499_50_504_508_51_512_516_52_524_528_540_548_554_558_56_562_566_578_586_591_598_600_604_608_616_620_624_626_630_634_638_64_642_643_646_662_678_68_682_686_688_694_70_702_703_704_705_706_710_716_72_724_728_729_740_748_752_756_76_760_762_764_768_780_784_788_792_795_8_800_804_807_818_826_834_84_840_854_858_860_862_882_887_894_90_96
A7: India | B7: 1450935791 | C7: 1.5 | D7: 17480 | E7: 0.5 | F7: =SUM(D7*E7) -> 8740 | G7: 11558 | H7: =SUM(F7+G7) -> 20298 | I7: 0.05 | J7: =SUM(H7*I7) -> 1014.9 | K7: 84.686699 | L7: =SUM(J7*Supuestos!$B$8) -> 101.49

Sheet Clinical_Efficiency
A1: Metodo_Quirurgico | B1: Tipo_Cirugia | C1: Dias_Internacion_Min | D1: Dias_Internacion_Max | E1: Dias_ Internacion_ Promedio | F1: Tasa_Complicaciones_Min_Porc | G1: Tasa_Complicaciones_Max_Porc | H1: Tasa_ Complicaciones_ Promedio_ Porc | I1: Dias_Recuperacion_Min | J1: Dias_Recuperacion_Max | K1: Dias_ Recuperacion_ Promedio | L1: Reduccion_Costos_Min_Porc | M1: Reduccion_Costos_Max_Porc | N1: Reduccion_ Costos_ Promedio_ Porc | O1: Fuente_Estudio
A2: Cirugía abierta | B2: General | C2: 5 | D2: 7 | E2: 6 | F2: 15 | G2: 20 | H2: =(F2+G2)/2 -> 17.5 | I2: 30 | J2: 45 | K2: =(I2+J2)/2 -> 37.5 | L2: 45 | M2: 55 | N2: =(L2+M2)/2 -> 50 | O2: Ministerio de Salud / OMS
A3: Laparoscópica | B3: Mínimamente invasiva | C3: 2 | D3: 4 | E3: 3 | F3: 8 | G3: 12 | H3: =(F3+G3)/2 -> 10 | I3: 15 | J3: 25 | K3: =(I3+J3)/2 -> 20 | L3: 35 | M3: 45 | N3: =(L3+M3)/2 -> 40 | O3: NHS / OPS
A4: Robótica | B4: Mínimamente invasiva asistida | C4: 1 | D4: 3 | E4: 2 | F4: 5 | G4: 8 | H4: =(F4+G4)/2 -> 6.5 | I4: 7 | J4: 15 | K4: =(I4+J4)/2 -> 11 | L4: 5 | M4: 10 | N4: =(L4+M4)/2 -> 7.5 | O4: NIH / Estudios hospitales públicos

Sheet ROI
A1: Escenario | B1: Volumen_ Cirugias_ Min_ Anual | C1: Volumen_ Cirugias_ Max_ Anual | D1: Volumen_ Cirugias_ Promedio_ Anual | E1: Ahorro Total Anual | F1: Precio_ Robot_ USD | G1: ROI_Anos
A2: Hospital Público Chico | B2: 40 | C2: 60 | D2: =(Tabla3[[#This Row],[Volumen_ Cirugias_ Min_ Anual]]+Tabla3[[#This Row],[Volumen_ Cirugias_ Max_ Anual]])/2 -> 50 | E2: =Tabla3[[#This Row],[Volumen_ Cirugias_ Promedio_ Anual]]*Supuestos!$B$3 -> 96450 | F2: =Supuestos!$B$2 -> 750000 | G2: =Tabla3[[#This Row],[Precio_ Robot_ USD]]/Tabla3[[#This Row],[Ahorro Total Anual]] -> 7.7760498 | J2: El ahorro de 1.929 USD por procedimiento se calcula de forma independiente al ahorro porcentual operativo
A3: Hospital Público Mediano | B3: 100 | C3: 150 | D3: =(Tabla3[[#This Row],[Volumen_ Cirugias_ Min_ Anual]]+Tabla3[[#This Row],[Volumen_ Cirugias_ Max_ Anual]])/2 -> 125 | E3: =Tabla3[[#This Row],[Volumen_ Cirugias_ Promedio_ Anual]]*Supuestos!$B$3 -> 241125 | F3: =Supuestos!$B$2 -> 750000 | G3: =Tabla3[[#This Row],[Precio_ Robot_ USD]]/Tabla3[[#This Row],[Ahorro Total Anual]] -> 3.1104199 | J3: (7,5%), ya que contempla el impacto clínico directo: reducción de 1,5 días de internación promedio y
A4: Hospital Público Grande | B4: 250 | C4: 350 | D4: =(Tabla3[[#This Row],[Volumen_ Cirugias_ Min_ Anual]]+Tabla3[[#This Row],[Volumen_ Cirugias_ Max_ Anual]])/2 -> 300 | E4: =Tabla3[[#This Row],[Volumen_ Cirugias_ Promedio_ Anual]]*Supuestos!$B$3 -> 578700 | F4: =Supuestos!$B$2 -> 750000 | G4: =Tabla3[[#This Row],[Precio_ Robot_ USD]]/Tabla3[[#This Row],[Ahorro Total Anual]] -> 1.2960083 | J4: disminución de reintervenciones por complicaciones (Fuente: Benchmarks de cirugía robótica en nefrectomía)
J7: Para efectos de esta evaluación estratégica, el Retorno de Inversión (ROI) y el período de Payback se calculan
J8: sobre el Ahorro Bruto Directo generado por la liberación de recursos hospitalarios. Esta simplificación
J9: metodológica permite visualizar con claridad la capacidad de recuperación del capital invertido (CAPEX)
J10: frente al valor clínico entregado. Los costos operativos recurrentes, tales como el mantenimiento anual
J11: ($32.500 USD) y los seguros, se consideran en el flujo de caja operativo posterior y no afectan la métrica de
J12: recupero inicial aquí presentada.
J14: Interpretación Estratégica: El ROI de 7,77 años en el escenario "Chico" demuestra que el modelo de compra
J15: directa (CAPEX) no es financieramente óptimo para instituciones de bajo volumen, validando la propuesta de la
J16: Hipótesis 2 sobre la necesidad de modelos de Pago por Uso o Leasing.

Sheet Hospitales
A1: Hospital | B1: Provincia | C1: Sector | D1: Segmento Estratégico | E1: Nivel CAPEX | F1: ¿Tienen Robot Actual? | G1: Modelo Justina Propuesto
A2: Hospital Italiano | B2: Buenos Aires | C2: Privado | D2: Fase 1: Rentabilidad y Prestigio | E2: Alto | F2: SÍ (da Vinci) | G2: Venta Directa con Descuento
A3: Fundación Favaloro | B3: Buenos Aires | C3: Privado | D3: Fase 1: Rentabilidad y Prestigio | E3: Alto | F3: NO | G3: Venta Directa / Leasing
A4: Hospital Británico | B4: Buenos Aires | C4: Privado | D4: Fase 1: Rentabilidad y Prestigio | E4: Alto | F4: NO | G4: Venta Directa / Leasing
A5: Hospital Posadas | B5: Buenos Aires | C5: Público | D5: Fase 2: Volumen e Impacto | E5: Muy Bajo (Restringido) | F5: NO | G5: Pago por Uso
A6: Hospital El Cruce | B6: Buenos Aires | C6: Público | D6: Fase 2: Volumen e Impacto | E6: Bajo | F6: NO | G6: Pago por Uso
A7: Hospital Garrahan | B7: Buenos Aires | C7: Pediátrico Público | D7: Fase 3: Académico / Casos Especiales | E7: Subvencionado | F7: NO | G7: Comodato / I+D
A8: Hospital Alemán | B8: Buenos Aires | C8: Privado | D8: Fase 1: Rentabilidad y Prestigio | E8: Alto | F8: SÍ | G8: Venta Directa / Leasing
A9: Hospital Padilla | B9: Tucumán | C9: Público | D9: Fase 2: Volumen Regional | E9: Bajo | F9: NO | G9: Pago por Uso
A10: Hospital Vélez Sarsfield (Córdoba) | B10: Córdoba | C10: Público | D10: Fase 2: Volumen Regional | E10: Bajo | F10: NO | G10: Pago por Uso
A11: Sanatorio Güemes | B11: Buenos Aires | C11: Privado | D11: Fase 1: Rentabilidad y Prestigio | E11: Alto | F11: NO | G11: Venta Directa / Leasing
A12: Sanatorio Otamendi | B12: Buenos Aires | C12: Privado | D12: Fase 1: Rentabilidad y Prestigio | E12: Alto | F12: NO | G12: Venta Directa / Leasing
... A19: Hospital San Martín (La Plata) | B19: Buenos Aires | C19: Público | D19: Fase 2: Alta Complejidad Provincial | E19: Bajo | F19: NO | G19: Pago por Uso

Sheet Modelo adquisición
A1: Modelo de Adquisición | B1: Pago Inicial (Barrera de Entrada) | C1: Costo Fijo Anual (Años 1 al 5) | D1: Costo_ Consumibles_ Promedio_ USD | E1: Costo extra por cirugia | F1: Costo_Variable_ USD | G1: ¿Quién asume el riesgo? | H1: comentario
A2: 1. CAPEX Tradicional (Venta) | B2: =Supuestos!B2 -> 750000 | C2: 35000 | D2: =Competencia_Precio!$K$5 -> 450 | E2: 0 | F2: =D2+E2 -> 450 | G2: El Hospital | H2: $ 35.000 (A partir del Año 2)
A3: 2. Leasing Financiero (5 años) | B3: 0 | C3: 195000 | D3: =Competencia_Precio!$K$5 -> 450 | E3: 0 | F3: =D3+E3 -> 450 | G3: Riesgo Compartido | H3: $ 195.000 (Incluye mantenimiento)
A4: 3. Pago por Uso (Comodato) | B4: 0 | C4: 0 | D4: =Competencia_Precio!$K$5 -> 450 | E4: 1500 | F4: =D4+E4 -> 1950 | G4: Justina (La Empresa) | H4: $ 1.500 extra por cirugía
